{"nodes": [{"id": "d_music_music_player_working_artifacts_api_server_src_routes_music_ts", "label": "music.ts", "file_type": "code", "source_file": "D:\\Music\\Music-Player-Working\\artifacts\\api-server\\src\\routes\\music.ts", "source_location": "L1"}, {"id": "music_runpython", "label": "runPython()", "file_type": "code", "source_file": "D:\\Music\\Music-Player-Working\\artifacts\\api-server\\src\\routes\\music.ts", "source_location": "L20"}, {"id": "music_normalizethumbnails", "label": "normalizeThumbnails()", "file_type": "code", "source_file": "D:\\Music\\Music-Player-Working\\artifacts\\api-server\\src\\routes\\music.ts", "source_location": "L41"}, {"id": "music_normalizetrack", "label": "normalizeTrack()", "file_type": "code", "source_file": "D:\\Music\\Music-Player-Working\\artifacts\\api-server\\src\\routes\\music.ts", "source_location": "L50"}], "edges": [{"source": "d_music_music_player_working_artifacts_api_server_src_routes_music_ts", "target": "express", "relation": "imports_from", "confidence": "EXTRACTED", "source_file": "D:\\Music\\Music-Player-Working\\artifacts\\api-server\\src\\routes\\music.ts", "source_location": "L1", "weight": 1.0}, {"source": "d_music_music_player_working_artifacts_api_server_src_routes_music_ts", "target": "child_process", "relation": "imports_from", "confidence": "EXTRACTED", "source_file": "D:\\Music\\Music-Player-Working\\artifacts\\api-server\\src\\routes\\music.ts", "source_location": "L2", "weight": 1.0}, {"source": "d_music_music_player_working_artifacts_api_server_src_routes_music_ts", "target": "api_zod", "relation": "imports_from", "confidence": "EXTRACTED", "source_file": "D:\\Music\\Music-Player-Working\\artifacts\\api-server\\src\\routes\\music.ts", "source_location": "L3", "weight": 1.0}, {"source": "d_music_music_player_working_artifacts_api_server_src_routes_music_ts", "target": "music_runpython", "relation": "contains", "confidence": "EXTRACTED", "source_file": "D:\\Music\\Music-Player-Working\\artifacts\\api-server\\src\\routes\\music.ts", "source_location": "L20", "weight": 1.0}, {"source": "d_music_music_player_working_artifacts_api_server_src_routes_music_ts", "target": "music_normalizethumbnails", "relation": "contains", "confidence": "EXTRACTED", "source_file": "D:\\Music\\Music-Player-Working\\artifacts\\api-server\\src\\routes\\music.ts", "source_location": "L41", "weight": 1.0}, {"source": "d_music_music_player_working_artifacts_api_server_src_routes_music_ts", "target": "music_normalizetrack", "relation": "contains", "confidence": "EXTRACTED", "source_file": "D:\\Music\\Music-Player-Working\\artifacts\\api-server\\src\\routes\\music.ts", "source_location": "L50", "weight": 1.0}, {"source": "music_normalizetrack", "target": "music_normalizethumbnails", "relation": "calls", "confidence": "EXTRACTED", "source_file": "D:\\Music\\Music-Player-Working\\artifacts\\api-server\\src\\routes\\music.ts", "source_location": "L65", "weight": 1.0}], "raw_calls": [{"caller_nid": "music_normalizethumbnails", "callee": "isArray", "source_file": "D:\\Music\\Music-Player-Working\\artifacts\\api-server\\src\\routes\\music.ts", "source_location": "L42"}, {"caller_nid": "music_normalizethumbnails", "callee": "map", "source_file": "D:\\Music\\Music-Player-Working\\artifacts\\api-server\\src\\routes\\music.ts", "source_location": "L43"}, {"caller_nid": "music_normalizetrack", "callee": "isArray", "source_file": "D:\\Music\\Music-Player-Working\\artifacts\\api-server\\src\\routes\\music.ts", "source_location": "L51"}, {"caller_nid": "music_normalizetrack", "callee": "map", "source_file": "D:\\Music\\Music-Player-Working\\artifacts\\api-server\\src\\routes\\music.ts", "source_location": "L52"}]}